webcap/__init__.py
webcap/base.py
webcap/browser.py
webcap/cli.py
webcap/defaults.py
webcap/errors.py
webcap/helpers.py
webcap/imagehash.py
webcap/javascript.py
webcap/server/__init__.py
webcap/server/server.py
webcap/server/static/react-dom.production.min.js
webcap/server/static/react.production.min.js
webcap/server/static/webcap.png
webcap/server/templates/index.html
webcap/tab.py
webcap/webscreenshot.py
webcap-0.1.97.dist-info/LICENSE
webcap-0.1.97.dist-info/METADATA
webcap-0.1.97.dist-info/WHEEL
webcap-0.1.97.dist-info/entry_points.txt
webcap-0.1.97.dist-info/RECORD
