Metadata-Version: 2.3
Name: webcap
Version: 0.1.97
Summary: An ultra-lightweight web screenshot tool written in Python
License: GPL-v3.0
Keywords: python,cli,web,screenshot,osint,ocr,bug-bounty,bugbounty,headless,web-browser,scanner,python-library,hacking,pentesting,recon
Author: TheTechromancer
Requires-Python: >=3.9,<3.14
Classifier: License :: Other/Proprietary License
Classifier: Operating System :: POSIX :: Linux
Classifier: Programming Language :: Python :: 3
Classifier: Programming Language :: Python :: 3.9
Classifier: Programming Language :: Python :: 3.10
Classifier: Programming Language :: Python :: 3.11
Classifier: Programming Language :: Python :: 3.12
Classifier: Programming Language :: Python :: 3.13
Classifier: Topic :: Security
Requires-Dist: extractous (>=0.3.0,<0.4.0)
Requires-Dist: fastapi (>=0.115.6,<0.116.0)
Requires-Dist: httpx (>=0.28.0,<0.29.0)
Requires-Dist: numpy (>=2.0.2,<2.1.0)
Requires-Dist: orjson (>=3.10.12,<4.0.0)
Requires-Dist: pillow (>=11.1.0,<12.0.0)
Requires-Dist: rich (>=13.9.4,<14.0.0)
Requires-Dist: typer (>=0.15.2,<0.16.0)
Requires-Dist: uvicorn (>=0.34.0,<0.35.0)
Requires-Dist: uvloop (>=0.21.0,<0.22.0)
Requires-Dist: websockets (>=14.1,<16.0)
Project-URL: Homepage, https://github.com/blacklanternsecurity/webcap
Project-URL: Repository, https://github.com/blacklanternsecurity/webcap
